src/__init__.py
src/client.py
src/main.py
lightdash_mcp_server-1.0.36.dist-info/METADATA
lightdash_mcp_server-1.0.36.dist-info/WHEEL
lightdash_mcp_server-1.0.36.dist-info/entry_points.txt
lightdash_mcp_server-1.0.36.dist-info/licenses/LICENSE
lightdash_mcp_server-1.0.36.dist-info/RECORD
