Metadata-Version: 2.4
Name: lightdash-mcp-server
Version: 1.0.36
Summary: MCP server bridge for Lightdash analytics platform
Project-URL: Homepage, https://github.com/yourusername/lightdash-mcp-server
Author-email: Bratrax <bratrax@example.com>
Maintainer-email: Bratrax <bratrax@example.com>
License: MIT
License-File: LICENSE
Requires-Dist: httpx>=0.25.0
Requires-Dist: mcp>=1.0.0
